gcloud/py.typed
gcloud/rest/datastore/__init__.py
gcloud/rest/datastore/array.py
gcloud/rest/datastore/constants.py
gcloud/rest/datastore/datastore.py
gcloud/rest/datastore/datastore_operation.py
gcloud/rest/datastore/entity.py
gcloud/rest/datastore/filter.py
gcloud/rest/datastore/key.py
gcloud/rest/datastore/lat_lng.py
gcloud/rest/datastore/mutation.py
gcloud/rest/datastore/projection.py
gcloud/rest/datastore/property_order.py
gcloud/rest/datastore/py.typed
gcloud/rest/datastore/query.py
gcloud/rest/datastore/query_explain.py
gcloud/rest/datastore/transaction_options.py
gcloud/rest/datastore/value.py
gcloud/rest/py.typed
gcloud_rest_datastore-9.1.0.dist-info/LICENSE
gcloud_rest_datastore-9.1.0.dist-info/METADATA
gcloud_rest_datastore-9.1.0.dist-info/WHEEL
gcloud_rest_datastore-9.1.0.dist-info/RECORD
